<?xml version="1.0" encoding="UTF-8"?>
<con:resource name="" path="Vse" id="ee7deba0-05f2-44a8-9cd5-030e30f93d2e" xmlns:xsi="http://www.w3.org/2001/XMLSchema-instance" xmlns:con="http://eviware.com/soapui/config">
  <con:settings>
    <con:setting id="ee7deba0-05f2-44a8-9cd5-030e30f93d2efileName">Vse</con:setting>
  </con:settings>
  <con:parameters/>
  <con:method name="" id="88772b26-ec9f-47de-aedc-28ee3b33b085" method="GET">
    <con:settings/>
    <con:parameters>
      <con:parameter>
        <con:name>x</con:name>
        <con:value xsi:nil="true"/>
        <con:style>QUERY</con:style>
        <con:type xmlns:xs="http://www.w3.org/2001/XMLSchema">xs:integer</con:type>
        <con:default xsi:nil="true"/>
      </con:parameter>
      <con:parameter>
        <con:name>y</con:name>
        <con:value xsi:nil="true"/>
        <con:style>QUERY</con:style>
        <con:type xmlns:xs="http://www.w3.org/2001/XMLSchema">xs:integer</con:type>
        <con:default xsi:nil="true"/>
      </con:parameter>
      <con:parameter>
        <con:name>z</con:name>
        <con:value xsi:nil="true"/>
        <con:style>QUERY</con:style>
        <con:default xsi:nil="true"/>
      </con:parameter>
    </con:parameters>
    <con:request name="Request 1" id="9698ceb7-5bb2-41d1-9a6c-40cb11ae9a74" mediaType="application/json">
      <con:settings/>
      <con:endpoint>http://rapis02.aqa.com.ru</con:endpoint>
      <con:request/>
      <con:credentials>
        <con:selectedAuthProfile>No Authorization</con:selectedAuthProfile>
        <con:authType>No Authorization</con:authType>
      </con:credentials>
      <con:jmsConfig JMSDeliveryMode="PERSISTENT"/>
      <con:parameters/>
      <con:parameterOrder>
        <con:entry>x</con:entry>
        <con:entry>y</con:entry>
        <con:entry>z</con:entry>
      </con:parameterOrder>
      <con:environmentSpec>
        <con:entry environmentId="b771e1b5-6212-4a18-8dc7-931d1e1d9e4d">
          <con:authProfile>No Authorization</con:authProfile>
        </con:entry>
      </con:environmentSpec>
    </con:request>
  </con:method>
</con:resource>
